pyPartAnalysis/__init__.py
pyPartAnalysis/analysis.py
pyPartAnalysis/bunching.py
pyPartAnalysis/convert.py
pyPartAnalysis/diffraction.py
pyPartAnalysis/particle_accelerator_utilities.py
pyPartAnalysis/plot.py
pyPartAnalysis/read.py
pyPartAnalysis/stripes.py
pyPartAnalysis/transform.py
pyPartAnalysis/twiss.py
pyPartAnalysis/write.py
py_particle_analysis-0.0.1.dist-info/LICENSE
py_particle_analysis-0.0.1.dist-info/METADATA
py_particle_analysis-0.0.1.dist-info/WHEEL
py_particle_analysis-0.0.1.dist-info/top_level.txt
py_particle_analysis-0.0.1.dist-info/RECORD
