Metadata-Version: 2.1
Name: py-particle-analysis
Version: 0.0.1
Summary: Python Package for particle distribution analysis with a focus on ImpactZ and ImpactT file types
Author-email: Lucas Malin <lukemalin@gmail.com>
License: MIT License
Project-URL: Homepage, https://github.com/lm314/py-particle-analysis
Project-URL: Bug Tracker, https://github.com/lm314/py-particle-analysis/issues
Classifier: Programming Language :: Python :: 3
Classifier: License :: OSI Approved :: MIT License
Classifier: Operating System :: OS Independent
Requires-Python: >=3.9
License-File: LICENSE
Requires-Dist: pandas (>=1.4.1)
Requires-Dist: numpy (>=1.20.3)
Requires-Dist: scikit-learn (>=1.0.2)
Requires-Dist: matplotlib (>=3.5.1)
Requires-Dist: numba (>=0.54.1)
